xquant/__init__.py
xquant/_time.py
xquant/api.py
xquant/cmd.py
xquant/context.py
xquant/data.py
xquant/global_config.py
xquant/utils.py
xquant/xquant.py
xquant/commands/xquant_cli
xquant/lib/__init__.py
xquant/lib/_xquant_analyser.cpython-36m-x86_64-linux-gnu.so
xquant/model/__init__.py
xquant/model/data_preprocess.py
xquant/model/data_process_methods.py
xquant/tools/__init__.py
xquant/tools/_checkparam.py
xquant/tools/_logger.py
xquant/tools/commonjson.py
xquant/tools/price_util.py
xquant/tools/time_util.py
xquant_python-3.0.295.dist-info/METADATA
xquant_python-3.0.295.dist-info/WHEEL
xquant_python-3.0.295.dist-info/entry_points.txt
xquant_python-3.0.295.dist-info/top_level.txt
xquant_python-3.0.295.dist-info/RECORD
